candleboy/__init__.py
candleboy/core.py
candleboy/exceptions.py
candleboy/api/__init__.py
candleboy/api/client.py
candleboy/tests/__init__.py
candleboy/tests/core_tests.py
candleboy-2.2.2.dist-info/LICENSE
candleboy-2.2.2.dist-info/WHEEL
candleboy-2.2.2.dist-info/METADATA
candleboy-2.2.2.dist-info/RECORD
