Metadata-Version: 2.1
Name: candleboy
Version: 2.2.2
Summary: Crypto exchange indicator application
Author-email: Marques Traylor <traylorboy@proton.me>
Classifier: License :: OSI Approved :: MIT License
Requires-Dist: phemexboy
Requires-Dist: TA-Lib
Requires-Dist: numpy
Project-URL: Home, https://github.com/TraylorBoy/CandleBoy
